py_simple_select/__init__.py
py_simple_select/main.py
Py_Simple_Select-1.0.0.dist-info/LICENSE
Py_Simple_Select-1.0.0.dist-info/METADATA
Py_Simple_Select-1.0.0.dist-info/WHEEL
Py_Simple_Select-1.0.0.dist-info/top_level.txt
Py_Simple_Select-1.0.0.dist-info/RECORD
