Metadata-Version: 2.1
Name: Py_Simple_Select
Version: 1.0.0
Summary: A lightweight ORM for SQLite with advanced and simplified select capabilities.
Home-page: https://github.com/gloacking/Py_Simple_Select
Author: Gloacking
Classifier: Programming Language :: Python :: 3
Classifier: License :: OSI Approved :: MIT License
Classifier: Operating System :: OS Independent
Requires-Python: >=3.10
License-File: LICENSE
